configistate/__init__.py
configistate/cli.py
configistate/config.py
configistate-1.0.0.dist-info/licenses/LICENSE
configistate-1.0.0.dist-info/METADATA
configistate-1.0.0.dist-info/WHEEL
configistate-1.0.0.dist-info/entry_points.txt
configistate-1.0.0.dist-info/top_level.txt
configistate-1.0.0.dist-info/RECORD
