Metadata-Version: 2.4
Name: configistate
Version: 1.0.0
Summary: Consistent, robust TOML config management with a friendly CLI
Author: Roger Trimble
License: MIT
Project-URL: Homepage, https://github.com/rtrimble13/configistate
Project-URL: Repository, https://github.com/rtrimble13/configistate
Project-URL: Issues, https://github.com/rtrimble13/configistate/issues
Project-URL: Changelog, https://github.com/rtrimble13/configistate/releases
Keywords: config,toml,cli,settings
Classifier: Development Status :: 3 - Alpha
Classifier: Intended Audience :: Developers
Classifier: Programming Language :: Python :: 3
Classifier: Programming Language :: Python :: 3.8
Classifier: Programming Language :: Python :: 3.9
Classifier: Programming Language :: Python :: 3.10
Classifier: Programming Language :: Python :: 3.11
Classifier: Programming Language :: Python :: 3.12
Classifier: Topic :: Utilities
Requires-Python: >=3.8
License-File: LICENSE
Requires-Dist: toml>=0.10.0
Requires-Dist: click>=8.0.0
Requires-Dist: tomli>=2.0; python_version < "3.11"
Provides-Extra: dev
Requires-Dist: pytest>=7.0.0; extra == "dev"
Requires-Dist: black>=22.0.0; extra == "dev"
Requires-Dist: flake8>=4.0.0; extra == "dev"
Requires-Dist: isort>=5.10.0; extra == "dev"
Dynamic: license-file
